{
  "sections": {
    "main": {
      "type": "main-product",
      "blocks": {
        "product_meta": {
          "type": "product_meta",
          "settings": {
            "show_vendor": false,
            "show_sku": false,
            "show_product_rating": false,
            "show_taxes_included": true
          }
        },
        "bf8ee223-cd27-4b9e-95f8-673e9625000b": {
          "type": "text_bulletpoints",
          "settings": {
            "text_bulletpoint_1": "Mehr Kontrolle",
            "text_bulletpoint_2": "Programmierbare Paddles",
            "text_bulletpoint_3": "Verbesserte Griffigkeit",
            "text_bulletpoint_4": "Handmade in Germany"
          }
        },
        "variant_selector": {
          "type": "variant_selector",
          "settings": {
            "selector_mode": "block",
            "show_color_swatch": false,
            "show_color_carousel": false,
            "size_chart": ""
          }
        },
        "quantity_selector": {
          "type": "quantity_selector",
          "settings": {
            "show_label": false
          }
        },
        "buy_buttons": {
          "type": "buy_buttons",
          "settings": {
            "show_price_in_button": false,
            "show_payment_button": false
          }
        },
        "c630c8c1-21a5-447f-ae58-7cd9cbbafc65": {
          "type": "paymentbuttons",
          "settings": {
          }
        },
        "6fba4ded-12d9-44c9-bd89-2c9bbc4c73f1": {
          "type": "description_01",
          "settings": {
            "title_description": "Beschreibung"
          }
        },
        "cdab740a-35b0-40d6-bb38-699be89a1a07": {
          "type": "content",
          "settings": {
            "title": "Versand",
            "content": "",
            "page": ""
          }
        },
        "e97968f1-b3c2-4bc4-8c0f-4db3c2f540a3": {
          "type": "benefits",
          "settings": {
            "image": "shopify:\/\/shop_images\/klarna_icon_7fad701a-9b2c-4800-9314-68d79d0e5bc5.png",
            "image2": "shopify:\/\/shop_images\/paypal2_icon_e444d04f-d647-4a6e-a356-4f006aa18d04.png",
            "text1": "Bezahle nach 30 Tagen",
            "text2": "Bezahle nach 30 Tagen"
          }
        },
        "7fab0125-f4b1-4dce-ba43-29719f70a9b6": {
          "type": "content",
          "settings": {
            "title": "",
            "content": "",
            "page": "versandkosten"
          }
        }
      },
      "block_order": [
        "product_meta",
        "bf8ee223-cd27-4b9e-95f8-673e9625000b",
        "variant_selector",
        "quantity_selector",
        "buy_buttons",
        "c630c8c1-21a5-447f-ae58-7cd9cbbafc65",
        "6fba4ded-12d9-44c9-bd89-2c9bbc4c73f1",
        "cdab740a-35b0-40d6-bb38-699be89a1a07",
        "e97968f1-b3c2-4bc4-8c0f-4db3c2f540a3",
        "7fab0125-f4b1-4dce-ba43-29719f70a9b6"
      ],
      "settings": {
        "image_size": "large",
        "stack_images": false,
        "show_thumbnails": true,
        "enable_image_zoom": true,
        "enable_video_looping": false
      }
    },
    "9b2b9dba-fae9-4579-a381-7889da79a61a": {
      "type": "image-with-text-overlay",
      "custom_css": [
        "p,h2,h3 {text-align: left; margin: 0;}",
        ".ImageHero {justify-content: left;}",
        ".SectionHeader {padding-left: 2rem;}",
        "@media (max-width: 768px) {p, h2, h3 {text-align: center; margin: 1rem; } .SectionHeader {padding-left: 0; }}"
      ],
      "settings": {
        "section_size": "small",
        "image": "shopify:\/\/shop_images\/PS5-Controller-Anleitung.png",
        "text_color": "#ffffff",
        "overlay_color": "#000000",
        "overlay_opacity": 30,
        "subheading": "100% Gaming",
        "title": "KING CONTROLLER",
        "content": "<p>Unsere King Controller gibt es in einer Vielzahl an Designs. Vom Minimalistischen bis hin zum ausgefallenen. Für jeden ist etwas dabei. Zusätzliche Tasten und Funktionen, sowie ein Softtouch-Grip machen die Controller zu einem besonderen Spielerlebnis. Unsere Swapsticks lassen sich bequem per Plug&Play in Farbe, Größe und Form austauschen um für jede Situation die passenden Aufsätze bereit zu haben.<\/p>"
      }
    },
    "c9c6bb98-513b-4c3a-b451-f47768bacdcf": {
      "type": "text_with_icons",
      "settings": {
        "img_left": true,
        "image": "shopify:\/\/shop_images\/SwapSticks.png",
        "title": "SWAPSTICKS",
        "text": "<p>Du bist es leid, deine Daumen für die Swap Sticks zu verkrampfen? Kein Problem, wir haben auch für deine \"Riesen-Pranken\" die passenden Swap Sticks!<\/p>"
      }
    },
    "847e321a-73cd-4b1f-90b7-21cde8df94f3": {
      "type": "text_with_icons",
      "settings": {
        "img_left": false,
        "image": "shopify:\/\/shop_images\/gamer-tag_443e3562-4f39-4cc0-a50a-545ff1bc8535.png",
        "title": "SOFTOUCH",
        "text": "<p>Unsere Controller sind mit einer speziellen Beschichtung versehen, die für eine optimale Handhabung sorgt. Damit bleibt der Controller auch bei rasanten, intensiven Spielen sicher in der Hand, und das Risiko eines Abrutschens wird minimiert.<\/p>"
      }
    },
    "ecbe35ff-1b89-4dc3-bf01-7c5265eea7a4": {
      "type": "text_with_icons",
      "settings": {
        "img_left": true,
        "image": "shopify:\/\/shop_images\/Quad-Curved.png",
        "title": "QUAD CURVED PADDLES",
        "text": "<p>Die neuen Quad-Curved bieten ein ganz neues Spielgefühl. Sie wurden dem Griff des Controllers angepasst, sodass man ohne Aufwand die Paddles bedienen kann, ganz ohne Eingewöhnungsphase.<\/p>"
      }
    },
    "5975615f-e7bf-4625-86e5-0859c994d174": {
      "type": "text_with_icons",
      "settings": {
        "img_left": false,
        "image": "shopify:\/\/shop_images\/Grip.png",
        "title": "PRO-GRIP",
        "text": "<p>Keine Lust mehr auf abrutschende Finger?<br\/>Der Grip sorgt für den optimalen Halt und sorgt dafür, dass keine deiner Bewegungen mehr abweicht und jede Reaktion punktgenau landet.<\/p>"
      }
    },
    "5095deeb-9d53-4b3d-843c-43770e55c564": {
      "type": "text_with_icons",
      "settings": {
        "img_left": true,
        "image": "shopify:\/\/shop_images\/bestseller.jpg",
        "title": "LIEFERUMFANG",
        "text": "<ul><li>PS5 Kin Controller in exklusivem Design<\/li><li>Swapsticks in Größe S<\/li><\/ul>"
      }
    },
    "f9589fb4-c4e6-43ba-99f2-daddeb985ec6": {
      "type": "text_with_icons",
      "custom_css": [
        ".twit_inner {background-color: #ffb1c7;}",
        "section {margin: 3rem 0;}",
        ".twit_block {margin: 0 3rem;}",
        "@media (min-width: 768px) {img {width: 50%; }}"
      ],
      "settings": {
        "img_left": true,
        "image": "shopify:\/\/shop_images\/Klarna_logo.png",
        "title": "PER RATEN ZAHLEN",
        "text": "<h3>MIT KLARNA.<\/h3>"
      }
    },
    "c2fe3a26-fc1c-4433-8c79-989353fe1b3f": {
      "type": "custom-html",
      "custom_css": [
        "h2,h3 {text-align: center;}"
      ],
      "settings": {
        "subheading": "",
        "title": "CHECK DAS MAL AUS",
        "html": ""
      }
    },
    "9f44038b-13f4-40bd-9408-630c88608eda": {
      "type": "featured-collections",
      "blocks": {
        "template--17943730389259__9f44038b-13f4-40bd-9408-630c88608eda-16867441458406dc1d-0": {
          "type": "collection",
          "settings": {
            "collection": "ps5-controller",
            "title": "",
            "grid_items_count": 4,
            "button_text": ""
          }
        }
      },
      "block_order": [
        "template--17943730389259__9f44038b-13f4-40bd-9408-630c88608eda-16867441458406dc1d-0"
      ],
      "custom_css": [
        "header {display: none;}"
      ],
      "settings": {
        "title": "",
        "layout_mode": "grid",
        "show_product_info": true,
        "show_vendor": false,
        "show_color_swatch": false,
        "grid_mobile_items_per_row": "2",
        "grid_desktop_items_per_row": 4
      }
    }
  },
  "order": [
    "main",
    "9b2b9dba-fae9-4579-a381-7889da79a61a",
    "c9c6bb98-513b-4c3a-b451-f47768bacdcf",
    "847e321a-73cd-4b1f-90b7-21cde8df94f3",
    "ecbe35ff-1b89-4dc3-bf01-7c5265eea7a4",
    "5975615f-e7bf-4625-86e5-0859c994d174",
    "5095deeb-9d53-4b3d-843c-43770e55c564",
    "f9589fb4-c4e6-43ba-99f2-daddeb985ec6",
    "c2fe3a26-fc1c-4433-8c79-989353fe1b3f",
    "9f44038b-13f4-40bd-9408-630c88608eda"
  ]
}
